recommender/__init__.py
recommender/core/__init__.py
recommender/core/base.py
recommender/core/data.py
recommender/core/trainers.py
recommender/data/__init__.py
recommender/data/datasets.py
recommender/data/preprocessing.py
recommender/data/samplers.py
recommender/evaluation/__init__.py
recommender/evaluation/evaluator.py
recommender/evaluation/metrics.py
recommender/models/__init__.py
recommender/models/factorization/__init__.py
recommender/models/factorization/als.py
recommender/models/factorization/svd.py
recommender/models/factorization/svd_plus_plus.py
recommender/models/graph/__init__.py
recommender/models/graph/lightgcn.py
recommender/models/neural/__init__.py
recommender/models/neural/ncf.py
recommender/models/sequential/__init__.py
recommender/models/sequential/sasrec.py
recommender/models/simple/__init__.py
recommender/models/simple/ease.py
recommender/models/simple/slim.py
recommender/serving/__init__.py
recommender/serving/api.py
recommender/utils/__init__.py
recommender/utils/faiss_index.py
recommender/utils/inference.py
sota_recommender-0.3.4.dist-info/licenses/LICENSE
sota_recommender-0.3.4.dist-info/METADATA
sota_recommender-0.3.4.dist-info/WHEEL
sota_recommender-0.3.4.dist-info/top_level.txt
sota_recommender-0.3.4.dist-info/RECORD
