Metadata-Version: 2.4
Name: sota-recommender
Version: 0.3.4
Summary: A modern, production-ready library for state-of-the-art recommender systems
Home-page: https://github.com/hichnicksemen/svd-recommender
Author: Semen Lobachevskiy
Author-email: hichnick@gmail.com
Project-URL: Bug Reports, https://github.com/hichnicksemen/svd-recommender/issues
Project-URL: Source, https://github.com/hichnicksemen/svd-recommender
Keywords: recommender-systems,machine-learning,deep-learning,collaborative-filtering,matrix-factorization
Classifier: Development Status :: 4 - Beta
Classifier: Intended Audience :: Developers
Classifier: Intended Audience :: Science/Research
Classifier: Topic :: Scientific/Engineering :: Artificial Intelligence
Classifier: Programming Language :: Python :: 3
Classifier: Programming Language :: Python :: 3.8
Classifier: Programming Language :: Python :: 3.9
Classifier: Programming Language :: Python :: 3.10
Classifier: Programming Language :: Python :: 3.11
Classifier: License :: OSI Approved :: MIT License
Classifier: Operating System :: OS Independent
Requires-Python: >=3.8
License-File: LICENSE
Requires-Dist: numpy>=1.20.0
Requires-Dist: pandas>=1.3.0
Requires-Dist: scikit-learn>=1.0.0
Requires-Dist: scipy>=1.7.0
Provides-Extra: torch
Requires-Dist: torch>=2.0.0; extra == "torch"
Requires-Dist: tqdm>=4.60.0; extra == "torch"
Provides-Extra: gnn
Requires-Dist: torch>=2.0.0; extra == "gnn"
Requires-Dist: torch-geometric>=2.3.0; extra == "gnn"
Provides-Extra: optimization
Requires-Dist: optuna>=3.0.0; extra == "optimization"
Provides-Extra: serving
Requires-Dist: faiss-cpu>=1.7.0; extra == "serving"
Requires-Dist: fastapi>=0.100.0; extra == "serving"
Requires-Dist: uvicorn>=0.23.0; extra == "serving"
Provides-Extra: dev
Requires-Dist: pytest>=7.0.0; extra == "dev"
Requires-Dist: pytest-cov>=4.0.0; extra == "dev"
Requires-Dist: black>=23.0.0; extra == "dev"
Requires-Dist: flake8>=6.0.0; extra == "dev"
Requires-Dist: mypy>=1.0.0; extra == "dev"
Provides-Extra: all
Requires-Dist: tqdm>=4.60.0; extra == "all"
Requires-Dist: pytest-cov>=4.0.0; extra == "all"
Requires-Dist: flake8>=6.0.0; extra == "all"
Requires-Dist: pytest>=7.0.0; extra == "all"
Requires-Dist: torch-geometric>=2.3.0; extra == "all"
Requires-Dist: uvicorn>=0.23.0; extra == "all"
Requires-Dist: black>=23.0.0; extra == "all"
Requires-Dist: fastapi>=0.100.0; extra == "all"
Requires-Dist: torch>=2.0.0; extra == "all"
Requires-Dist: optuna>=3.0.0; extra == "all"
Requires-Dist: mypy>=1.0.0; extra == "all"
Requires-Dist: faiss-cpu>=1.7.0; extra == "all"
Dynamic: author
Dynamic: author-email
Dynamic: classifier
Dynamic: description
Dynamic: description-content-type
Dynamic: home-page
Dynamic: keywords
Dynamic: license-file
Dynamic: project-url
Dynamic: provides-extra
Dynamic: requires-dist
Dynamic: requires-python
Dynamic: summary
